public final class uk/shusek/krwa/$gen/CompiledMachine implements uk/shusek/krwa/runtime/Machine {

  private final Luk/shusek/krwa/runtime/Instance; instance

  public <init>(Luk/shusek/krwa/runtime/Instance;)V
    ALOAD 0
    INVOKESPECIAL java/lang/Object.<init> ()V
    ALOAD 0
    ALOAD 1
    PUTFIELD uk/shusek/krwa/$gen/CompiledMachine.instance : Luk/shusek/krwa/runtime/Instance;
    RETURN

  public call(I[J)[J
    TRYCATCHBLOCK L0 L1 L1 java/lang/StackOverflowError
   L0
    ALOAD 0
    GETFIELD uk/shusek/krwa/$gen/CompiledMachine.instance : Luk/shusek/krwa/runtime/Instance;
    DUP
    INVOKEVIRTUAL uk/shusek/krwa/runtime/Instance.memory ()Luk/shusek/krwa/runtime/Memory;
    ILOAD 1
    ALOAD 2
    INVOKESTATIC uk/shusek/krwa/$gen/CompiledMachineMachineCall.call (Luk/shusek/krwa/runtime/Instance;Luk/shusek/krwa/runtime/Memory;I[J)[J
    ARETURN
   L1
    INVOKESTATIC uk/shusek/krwa/$gen/CompiledMachineShaded.throwCallStackExhausted (Ljava/lang/StackOverflowError;)Ljava/lang/RuntimeException;
    ATHROW

  public static call_indirect_0(IIILuk/shusek/krwa/runtime/Memory;Luk/shusek/krwa/runtime/Instance;)I
    INVOKESTATIC uk/shusek/krwa/$gen/CompiledMachineShaded.checkInterruption ()V
    ALOAD 4
    ILOAD 2
    INVOKEVIRTUAL uk/shusek/krwa/runtime/Instance.table (I)Luk/shusek/krwa/runtime/TableInstance;
    ASTORE 5
    ALOAD 5
    ILOAD 1
    INVOKEVIRTUAL uk/shusek/krwa/runtime/TableInstance.requiredRef (I)I
    ISTORE 6
    ALOAD 5
    ILOAD 1
    INVOKEVIRTUAL uk/shusek/krwa/runtime/TableInstance.instance (I)Luk/shusek/krwa/runtime/Instance;
    ASTORE 7
    ALOAD 7
    IFNULL L0
    ALOAD 7
    ALOAD 4
    IF_ACMPNE L1
   L0
    ILOAD 0
    ALOAD 3
    ALOAD 4
    ILOAD 6
    LOOKUPSWITCH
      0: L2
      1: L3
      2: L4
      3: L5
      4: L6
      5: L7
      6: L8
      7: L9
      8: L10
      9: L11
      default: L12
   L2
    INVOKESTATIC uk/shusek/krwa/$gen/CompiledMachineFuncGroup_0.func_0 (ILuk/shusek/krwa/runtime/Memory;Luk/shusek/krwa/runtime/Instance;)I
    IRETURN
   L3
    INVOKESTATIC uk/shusek/krwa/$gen/CompiledMachineFuncGroup_0.func_1 (ILuk/shusek/krwa/runtime/Memory;Luk/shusek/krwa/runtime/Instance;)I
    IRETURN
   L4
    INVOKESTATIC uk/shusek/krwa/$gen/CompiledMachineFuncGroup_0.func_2 (ILuk/shusek/krwa/runtime/Memory;Luk/shusek/krwa/runtime/Instance;)I
    IRETURN
   L5
    INVOKESTATIC uk/shusek/krwa/$gen/CompiledMachineFuncGroup_0.func_3 (ILuk/shusek/krwa/runtime/Memory;Luk/shusek/krwa/runtime/Instance;)I
    IRETURN
   L6
    INVOKESTATIC uk/shusek/krwa/$gen/CompiledMachineFuncGroup_0.func_4 (ILuk/shusek/krwa/runtime/Memory;Luk/shusek/krwa/runtime/Instance;)I
    IRETURN
   L7
    INVOKESTATIC uk/shusek/krwa/$gen/CompiledMachineFuncGroup_1.func_5 (ILuk/shusek/krwa/runtime/Memory;Luk/shusek/krwa/runtime/Instance;)I
    IRETURN
   L8
    INVOKESTATIC uk/shusek/krwa/$gen/CompiledMachineFuncGroup_1.func_6 (ILuk/shusek/krwa/runtime/Memory;Luk/shusek/krwa/runtime/Instance;)I
    IRETURN
   L9
    INVOKESTATIC uk/shusek/krwa/$gen/CompiledMachineFuncGroup_1.func_7 (ILuk/shusek/krwa/runtime/Memory;Luk/shusek/krwa/runtime/Instance;)I
    IRETURN
   L10
    INVOKESTATIC uk/shusek/krwa/$gen/CompiledMachineFuncGroup_1.func_8 (ILuk/shusek/krwa/runtime/Memory;Luk/shusek/krwa/runtime/Instance;)I
    IRETURN
   L11
    INVOKESTATIC uk/shusek/krwa/$gen/CompiledMachineFuncGroup_1.func_9 (ILuk/shusek/krwa/runtime/Memory;Luk/shusek/krwa/runtime/Instance;)I
    IRETURN
   L12
    INVOKESTATIC uk/shusek/krwa/$gen/CompiledMachineShaded.throwIndirectCallTypeMismatch ()Ljava/lang/RuntimeException;
    ATHROW
   L1
    ICONST_1
    NEWARRAY T_LONG
    DUP
    ICONST_0
    ILOAD 0
    I2L
    LASTORE
    ICONST_0
    ILOAD 6
    ALOAD 7
    INVOKESTATIC uk/shusek/krwa/$gen/CompiledMachineShaded.callIndirect ([JIILuk/shusek/krwa/runtime/Instance;)[J
    ICONST_0
    LALOAD
    L2I
    IRETURN
}

final class uk/shusek/krwa/$gen/CompiledMachineFuncGroup_0 {

  public static func_0(ILuk/shusek/krwa/runtime/Memory;Luk/shusek/krwa/runtime/Instance;)I
    ILOAD 0
    ICONST_1
    IADD
    IRETURN

  public static call_0(Luk/shusek/krwa/runtime/Instance;Luk/shusek/krwa/runtime/Memory;[J)[J
    ALOAD 2
    ICONST_0
    LALOAD
    L2I
    ALOAD 1
    ALOAD 0
    INVOKESTATIC uk/shusek/krwa/$gen/CompiledMachineFuncGroup_0.func_0 (ILuk/shusek/krwa/runtime/Memory;Luk/shusek/krwa/runtime/Instance;)I
    I2L
    LSTORE 3
    ICONST_1
    NEWARRAY T_LONG
    DUP
    ICONST_0
    LLOAD 3
    LASTORE
    ARETURN

  public static func_1(ILuk/shusek/krwa/runtime/Memory;Luk/shusek/krwa/runtime/Instance;)I
    ILOAD 0
    ICONST_2
    IADD
    INVOKESTATIC uk/shusek/krwa/$gen/CompiledMachineShaded.checkInterruption ()V
    ALOAD 1
    ALOAD 2
    INVOKESTATIC uk/shusek/krwa/$gen/CompiledMachineFuncGroup_0.func_0 (ILuk/shusek/krwa/runtime/Memory;Luk/shusek/krwa/runtime/Instance;)I
    IRETURN

  public static call_1(Luk/shusek/krwa/runtime/Instance;Luk/shusek/krwa/runtime/Memory;[J)[J
    ALOAD 2
    ICONST_0
    LALOAD
    L2I
    ALOAD 1
    ALOAD 0
    INVOKESTATIC uk/shusek/krwa/$gen/CompiledMachineFuncGroup_0.func_1 (ILuk/shusek/krwa/runtime/Memory;Luk/shusek/krwa/runtime/Instance;)I
    I2L
    LSTORE 3
    ICONST_1
    NEWARRAY T_LONG
    DUP
    ICONST_0
    LLOAD 3
    LASTORE
    ARETURN

  public static func_2(ILuk/shusek/krwa/runtime/Memory;Luk/shusek/krwa/runtime/Instance;)I
    ILOAD 0
    ICONST_3
    IADD
    INVOKESTATIC uk/shusek/krwa/$gen/CompiledMachineShaded.checkInterruption ()V
    ALOAD 1
    ALOAD 2
    INVOKESTATIC uk/shusek/krwa/$gen/CompiledMachineFuncGroup_0.func_1 (ILuk/shusek/krwa/runtime/Memory;Luk/shusek/krwa/runtime/Instance;)I
    IRETURN

  public static call_2(Luk/shusek/krwa/runtime/Instance;Luk/shusek/krwa/runtime/Memory;[J)[J
    ALOAD 2
    ICONST_0
    LALOAD
    L2I
    ALOAD 1
    ALOAD 0
    INVOKESTATIC uk/shusek/krwa/$gen/CompiledMachineFuncGroup_0.func_2 (ILuk/shusek/krwa/runtime/Memory;Luk/shusek/krwa/runtime/Instance;)I
    I2L
    LSTORE 3
    ICONST_1
    NEWARRAY T_LONG
    DUP
    ICONST_0
    LLOAD 3
    LASTORE
    ARETURN

  public static func_3(ILuk/shusek/krwa/runtime/Memory;Luk/shusek/krwa/runtime/Instance;)I
    ILOAD 0
    ICONST_4
    IADD
    INVOKESTATIC uk/shusek/krwa/$gen/CompiledMachineShaded.checkInterruption ()V
    ALOAD 1
    ALOAD 2
    INVOKESTATIC uk/shusek/krwa/$gen/CompiledMachineFuncGroup_0.func_2 (ILuk/shusek/krwa/runtime/Memory;Luk/shusek/krwa/runtime/Instance;)I
    IRETURN

  public static call_3(Luk/shusek/krwa/runtime/Instance;Luk/shusek/krwa/runtime/Memory;[J)[J
    ALOAD 2
    ICONST_0
    LALOAD
    L2I
    ALOAD 1
    ALOAD 0
    INVOKESTATIC uk/shusek/krwa/$gen/CompiledMachineFuncGroup_0.func_3 (ILuk/shusek/krwa/runtime/Memory;Luk/shusek/krwa/runtime/Instance;)I
    I2L
    LSTORE 3
    ICONST_1
    NEWARRAY T_LONG
    DUP
    ICONST_0
    LLOAD 3
    LASTORE
    ARETURN

  public static func_4(ILuk/shusek/krwa/runtime/Memory;Luk/shusek/krwa/runtime/Instance;)I
    ILOAD 0
    ICONST_5
    IADD
    INVOKESTATIC uk/shusek/krwa/$gen/CompiledMachineShaded.checkInterruption ()V
    ALOAD 1
    ALOAD 2
    INVOKESTATIC uk/shusek/krwa/$gen/CompiledMachineFuncGroup_0.func_3 (ILuk/shusek/krwa/runtime/Memory;Luk/shusek/krwa/runtime/Instance;)I
    IRETURN

  public static call_4(Luk/shusek/krwa/runtime/Instance;Luk/shusek/krwa/runtime/Memory;[J)[J
    ALOAD 2
    ICONST_0
    LALOAD
    L2I
    ALOAD 1
    ALOAD 0
    INVOKESTATIC uk/shusek/krwa/$gen/CompiledMachineFuncGroup_0.func_4 (ILuk/shusek/krwa/runtime/Memory;Luk/shusek/krwa/runtime/Instance;)I
    I2L
    LSTORE 3
    ICONST_1
    NEWARRAY T_LONG
    DUP
    ICONST_0
    LLOAD 3
    LASTORE
    ARETURN
}

final class uk/shusek/krwa/$gen/CompiledMachineFuncGroup_1 {

  public static func_5(ILuk/shusek/krwa/runtime/Memory;Luk/shusek/krwa/runtime/Instance;)I
    ILOAD 0
    BIPUSH 6
    IADD
    INVOKESTATIC uk/shusek/krwa/$gen/CompiledMachineShaded.checkInterruption ()V
    ALOAD 1
    ALOAD 2
    INVOKESTATIC uk/shusek/krwa/$gen/CompiledMachineFuncGroup_0.func_4 (ILuk/shusek/krwa/runtime/Memory;Luk/shusek/krwa/runtime/Instance;)I
    IRETURN

  public static call_5(Luk/shusek/krwa/runtime/Instance;Luk/shusek/krwa/runtime/Memory;[J)[J
    ALOAD 2
    ICONST_0
    LALOAD
    L2I
    ALOAD 1
    ALOAD 0
    INVOKESTATIC uk/shusek/krwa/$gen/CompiledMachineFuncGroup_1.func_5 (ILuk/shusek/krwa/runtime/Memory;Luk/shusek/krwa/runtime/Instance;)I
    I2L
    LSTORE 3
    ICONST_1
    NEWARRAY T_LONG
    DUP
    ICONST_0
    LLOAD 3
    LASTORE
    ARETURN

  public static func_6(ILuk/shusek/krwa/runtime/Memory;Luk/shusek/krwa/runtime/Instance;)I
    ILOAD 0
    BIPUSH 7
    IADD
    INVOKESTATIC uk/shusek/krwa/$gen/CompiledMachineShaded.checkInterruption ()V
    ALOAD 1
    ALOAD 2
    INVOKESTATIC uk/shusek/krwa/$gen/CompiledMachineFuncGroup_1.func_5 (ILuk/shusek/krwa/runtime/Memory;Luk/shusek/krwa/runtime/Instance;)I
    IRETURN

  public static call_6(Luk/shusek/krwa/runtime/Instance;Luk/shusek/krwa/runtime/Memory;[J)[J
    ALOAD 2
    ICONST_0
    LALOAD
    L2I
    ALOAD 1
    ALOAD 0
    INVOKESTATIC uk/shusek/krwa/$gen/CompiledMachineFuncGroup_1.func_6 (ILuk/shusek/krwa/runtime/Memory;Luk/shusek/krwa/runtime/Instance;)I
    I2L
    LSTORE 3
    ICONST_1
    NEWARRAY T_LONG
    DUP
    ICONST_0
    LLOAD 3
    LASTORE
    ARETURN

  public static func_7(ILuk/shusek/krwa/runtime/Memory;Luk/shusek/krwa/runtime/Instance;)I
    ILOAD 0
    BIPUSH 8
    IADD
    INVOKESTATIC uk/shusek/krwa/$gen/CompiledMachineShaded.checkInterruption ()V
    ALOAD 1
    ALOAD 2
    INVOKESTATIC uk/shusek/krwa/$gen/CompiledMachineFuncGroup_1.func_6 (ILuk/shusek/krwa/runtime/Memory;Luk/shusek/krwa/runtime/Instance;)I
    IRETURN

  public static call_7(Luk/shusek/krwa/runtime/Instance;Luk/shusek/krwa/runtime/Memory;[J)[J
    ALOAD 2
    ICONST_0
    LALOAD
    L2I
    ALOAD 1
    ALOAD 0
    INVOKESTATIC uk/shusek/krwa/$gen/CompiledMachineFuncGroup_1.func_7 (ILuk/shusek/krwa/runtime/Memory;Luk/shusek/krwa/runtime/Instance;)I
    I2L
    LSTORE 3
    ICONST_1
    NEWARRAY T_LONG
    DUP
    ICONST_0
    LLOAD 3
    LASTORE
    ARETURN

  public static func_8(ILuk/shusek/krwa/runtime/Memory;Luk/shusek/krwa/runtime/Instance;)I
    ILOAD 0
    BIPUSH 9
    IADD
    INVOKESTATIC uk/shusek/krwa/$gen/CompiledMachineShaded.checkInterruption ()V
    ALOAD 1
    ALOAD 2
    INVOKESTATIC uk/shusek/krwa/$gen/CompiledMachineFuncGroup_1.func_7 (ILuk/shusek/krwa/runtime/Memory;Luk/shusek/krwa/runtime/Instance;)I
    IRETURN

  public static call_8(Luk/shusek/krwa/runtime/Instance;Luk/shusek/krwa/runtime/Memory;[J)[J
    ALOAD 2
    ICONST_0
    LALOAD
    L2I
    ALOAD 1
    ALOAD 0
    INVOKESTATIC uk/shusek/krwa/$gen/CompiledMachineFuncGroup_1.func_8 (ILuk/shusek/krwa/runtime/Memory;Luk/shusek/krwa/runtime/Instance;)I
    I2L
    LSTORE 3
    ICONST_1
    NEWARRAY T_LONG
    DUP
    ICONST_0
    LLOAD 3
    LASTORE
    ARETURN

  public static func_9(ILuk/shusek/krwa/runtime/Memory;Luk/shusek/krwa/runtime/Instance;)I
    ILOAD 0
    BIPUSH 10
    IADD
    INVOKESTATIC uk/shusek/krwa/$gen/CompiledMachineShaded.checkInterruption ()V
    ALOAD 1
    ALOAD 2
    INVOKESTATIC uk/shusek/krwa/$gen/CompiledMachineFuncGroup_1.func_8 (ILuk/shusek/krwa/runtime/Memory;Luk/shusek/krwa/runtime/Instance;)I
    IRETURN

  public static call_9(Luk/shusek/krwa/runtime/Instance;Luk/shusek/krwa/runtime/Memory;[J)[J
    ALOAD 2
    ICONST_0
    LALOAD
    L2I
    ALOAD 1
    ALOAD 0
    INVOKESTATIC uk/shusek/krwa/$gen/CompiledMachineFuncGroup_1.func_9 (ILuk/shusek/krwa/runtime/Memory;Luk/shusek/krwa/runtime/Instance;)I
    I2L
    LSTORE 3
    ICONST_1
    NEWARRAY T_LONG
    DUP
    ICONST_0
    LLOAD 3
    LASTORE
    ARETURN
}

final class uk/shusek/krwa/$gen/CompiledMachineMachineCall {

  public <init>()V
    ALOAD 0
    INVOKESPECIAL java/lang/Object.<init> ()V
    RETURN

  public static call(Luk/shusek/krwa/runtime/Instance;Luk/shusek/krwa/runtime/Memory;I[J)[J
    ALOAD 0
    ALOAD 1
    ALOAD 3
    ILOAD 2
    TABLESWITCH
      0: L0
      1: L1
      2: L2
      3: L3
      4: L4
      5: L5
      6: L6
      7: L7
      8: L8
      9: L9
      default: L10
   L0
    INVOKESTATIC uk/shusek/krwa/$gen/CompiledMachineFuncGroup_0.call_0 (Luk/shusek/krwa/runtime/Instance;Luk/shusek/krwa/runtime/Memory;[J)[J
    ARETURN
   L1
    INVOKESTATIC uk/shusek/krwa/$gen/CompiledMachineFuncGroup_0.call_1 (Luk/shusek/krwa/runtime/Instance;Luk/shusek/krwa/runtime/Memory;[J)[J
    ARETURN
   L2
    INVOKESTATIC uk/shusek/krwa/$gen/CompiledMachineFuncGroup_0.call_2 (Luk/shusek/krwa/runtime/Instance;Luk/shusek/krwa/runtime/Memory;[J)[J
    ARETURN
   L3
    INVOKESTATIC uk/shusek/krwa/$gen/CompiledMachineFuncGroup_0.call_3 (Luk/shusek/krwa/runtime/Instance;Luk/shusek/krwa/runtime/Memory;[J)[J
    ARETURN
   L4
    INVOKESTATIC uk/shusek/krwa/$gen/CompiledMachineFuncGroup_0.call_4 (Luk/shusek/krwa/runtime/Instance;Luk/shusek/krwa/runtime/Memory;[J)[J
    ARETURN
   L5
    INVOKESTATIC uk/shusek/krwa/$gen/CompiledMachineFuncGroup_1.call_5 (Luk/shusek/krwa/runtime/Instance;Luk/shusek/krwa/runtime/Memory;[J)[J
    ARETURN
   L6
    INVOKESTATIC uk/shusek/krwa/$gen/CompiledMachineFuncGroup_1.call_6 (Luk/shusek/krwa/runtime/Instance;Luk/shusek/krwa/runtime/Memory;[J)[J
    ARETURN
   L7
    INVOKESTATIC uk/shusek/krwa/$gen/CompiledMachineFuncGroup_1.call_7 (Luk/shusek/krwa/runtime/Instance;Luk/shusek/krwa/runtime/Memory;[J)[J
    ARETURN
   L8
    INVOKESTATIC uk/shusek/krwa/$gen/CompiledMachineFuncGroup_1.call_8 (Luk/shusek/krwa/runtime/Instance;Luk/shusek/krwa/runtime/Memory;[J)[J
    ARETURN
   L9
    INVOKESTATIC uk/shusek/krwa/$gen/CompiledMachineFuncGroup_1.call_9 (Luk/shusek/krwa/runtime/Instance;Luk/shusek/krwa/runtime/Memory;[J)[J
    ARETURN
   L10
    ILOAD 2
    INVOKESTATIC uk/shusek/krwa/$gen/CompiledMachineShaded.throwUnknownFunction (I)Ljava/lang/RuntimeException;
    ATHROW
}
